[{"SHIPPING_TIME":"3/18/2026 3:44:43 PM","SHIPPING_NO":"101S06Z3656576K0Q0AG01","INVOICE_NO":"X511081485","CARTON_NO":"ZS06012630551002","PALLET_NO":"MSZW2631800246","MODEL_NO":"G101STN01-4/01","FINAL_GRADE":"Z","PART_NO":"97.10G08.401","STOCK_IN_WEEK":"202610"},{"SHIPPING_TIME":"3/18/2026 3:44:43 PM","SHIPPING_NO":"101S06Z3656576K0Q0DD01","INVOICE_NO":"X511081485","CARTON_NO":"ZS06012630551002","PALLET_NO":"MSZW2631800246","MODEL_NO":"G101STN01-4/01","FINAL_GRADE":"Z","PART_NO":"97.10G08.401","STOCK_IN_WEEK":"202610"},{"SHIPPING_TIME":"3/18/2026 3:44:43 PM","SHIPPING_NO":"101S06Z3656576Q8D0AH01","INVOICE_NO":"X511081485","CARTON_NO":"ZS06012630551002","PALLET_NO":"MSZW2631800246","MODEL_NO":"G101STN01-4/01","FINAL_GRADE":"Z","PART_NO":"97.10G08.401","STOCK_IN_WEEK":"202610"},{"SHIPPING_TIME":"3/18/2026 3:44:43 PM","SHIPPING_NO":"101S06Z3656576Q8D0CE01","INVOICE_NO":"X511081485","CARTON_NO":"ZS06012630551002","PALLET_NO":"MSZW2631800246","MODEL_NO":"G101STN01-4/01","FINAL_GRADE":"Z","PART_NO":"97.10G08.401","STOCK_IN_WEEK":"202610"},{"SHIPPING_TIME":"3/18/2026 3:44:43 PM","SHIPPING_NO":"101S06Z3656576Q8D0EB01","INVOICE_NO":"X511081485","CARTON_NO":"ZS06012630551002","PALLET_NO":"MSZW2631800246","MODEL_NO":"G101STN01-4/01","FINAL_GRADE":"Z","PART_NO":"97.10G08.401","STOCK_IN_WEEK":"202610"},{"SHIPPING_TIME":"3/18/2026 3:44:43 PM","SHIPPING_NO":"101S06Z365657765M0CB01","INVOICE_NO":"X511081485","CARTON_NO":"ZS06012630551002","PALLET_NO":"MSZW2631800246","MODEL_NO":"G101STN01-4/01","FINAL_GRADE":"Z","PART_NO":"97.10G08.401","STOCK_IN_WEEK":"202610"},{"SHIPPING_TIME":"3/18/2026 3:44:43 PM","SHIPPING_NO":"101S06Z3656577D1G0ED01","INVOICE_NO":"X511081485","CARTON_NO":"ZS06012630551002","PALLET_NO":"MSZW2631800246","MODEL_NO":"G101STN01-4/01","FINAL_GRADE":"Z","PART_NO":"97.10G08.401","STOCK_IN_WEEK":"202610"},{"SHIPPING_TIME":"3/18/2026 3:44:43 PM","SHIPPING_NO":"101S06Z3656577D1G0EG01","INVOICE_NO":"X511081485","CARTON_NO":"ZS06012630551002","PALLET_NO":"MSZW2631800246","MODEL_NO":"G101STN01-4/01","FINAL_GRADE":"Z","PART_NO":"97.10G08.401","STOCK_IN_WEEK":"202610"},{"SHIPPING_TIME":"3/18/2026 3:44:43 PM","SHIPPING_NO":"101S06Z3656577D1H0EE01","INVOICE_NO":"X511081485","CARTON_NO":"ZS06012630551002","PALLET_NO":"MSZW2631800246","MODEL_NO":"G101STN01-4/01","FINAL_GRADE":"Z","PART_NO":"97.10G08.401","STOCK_IN_WEEK":"202610"},{"SHIPPING_TIME":"3/18/2026 3:44:43 PM","SHIPPING_NO":"101S06Z3656577D1L0EC01","INVOICE_NO":"X511081485","CARTON_NO":"ZS06012630551002","PALLET_NO":"MSZW2631800246","MODEL_NO":"G101STN01-4/01","FINAL_GRADE":"Z","PART_NO":"97.10G08.401","STOCK_IN_WEEK":"202610"},{"SHIPPING_TIME":"3/18/2026 3:44:43 PM","SHIPPING_NO":"101S06Z3656577D1Q0AB01","INVOICE_NO":"X511081485","CARTON_NO":"ZS06012630551002","PALLET_NO":"MSZW2631800246","MODEL_NO":"G101STN01-4/01","FINAL_GRADE":"Z","PART_NO":"97.10G08.401","STOCK_IN_WEEK":"202610"},{"SHIPPING_TIME":"3/18/2026 3:44:43 PM","SHIPPING_NO":"101S06Z3656577D1Q0AC01","INVOICE_NO":"X511081485","CARTON_NO":"ZS06012630551002","PALLET_NO":"MSZW2631800246","MODEL_NO":"G101STN01-4/01","FINAL_GRADE":"Z","PART_NO":"97.10G08.401","STOCK_IN_WEEK":"202610"},{"SHIPPING_TIME":"3/18/2026 3:44:43 PM","SHIPPING_NO":"101S06Z3656577D1Q0BH01","INVOICE_NO":"X511081485","CARTON_NO":"ZS06012630551002","PALLET_NO":"MSZW2631800246","MODEL_NO":"G101STN01-4/01","FINAL_GRADE":"Z","PART_NO":"97.10G08.401","STOCK_IN_WEEK":"202610"},{"SHIPPING_TIME":"3/18/2026 3:44:43 PM","SHIPPING_NO":"101S06Z3656577D1S0DE01","INVOICE_NO":"X511081485","CARTON_NO":"ZS06012630551002","PALLET_NO":"MSZW2631800246","MODEL_NO":"G101STN01-4/01","FINAL_GRADE":"Z","PART_NO":"97.10G08.401","STOCK_IN_WEEK":"202610"},{"SHIPPING_TIME":"3/18/2026 3:44:43 PM","SHIPPING_NO":"101S06Z3656577D1W0AH01","INVOICE_NO":"X511081485","CARTON_NO":"ZS06012630551002","PALLET_NO":"MSZW2631800246","MODEL_NO":"G101STN01-4/01","FINAL_GRADE":"Z","PART_NO":"97.10G08.401","STOCK_IN_WEEK":"202610"},{"SHIPPING_TIME":"3/18/2026 3:44:43 PM","SHIPPING_NO":"101S06Z3656577D1W0CF01","INVOICE_NO":"X511081485","CARTON_NO":"ZS06012630551002","PALLET_NO":"MSZW2631800246","MODEL_NO":"G101STN01-4/01","FINAL_GRADE":"Z","PART_NO":"97.10G08.401","STOCK_IN_WEEK":"202610"},{"SHIPPING_TIME":"3/18/2026 3:44:43 PM","SHIPPING_NO":"431S06Z365558GE1J0DG01","INVOICE_NO":"X511081485","CARTON_NO":"ZS060125A2651065","PALLET_NO":"MSZW2631800246","MODEL_NO":"G101STN01-4/01","FINAL_GRADE":"Z","PART_NO":"97.10G08.401","STOCK_IN_WEEK":"202544"},{"SHIPPING_TIME":"3/18/2026 3:44:43 PM","SHIPPING_NO":"431S06Z365559195F0AB01","INVOICE_NO":"X511081485","CARTON_NO":"ZS060125A2651048","PALLET_NO":"MSZW2631800246","MODEL_NO":"G101STN01-4/01","FINAL_GRADE":"Z","PART_NO":"97.10G08.401","STOCK_IN_WEEK":"202544"},{"SHIPPING_TIME":"3/18/2026 3:44:43 PM","SHIPPING_NO":"431S06Z365559199R0EH01","INVOICE_NO":"X511081485","CARTON_NO":"ZS060125A2651065","PALLET_NO":"MSZW2631800246","MODEL_NO":"G101STN01-4/01","FINAL_GRADE":"Z","PART_NO":"97.10G08.401","STOCK_IN_WEEK":"202544"},{"SHIPPING_TIME":"3/18/2026 3:44:43 PM","SHIPPING_NO":"431S06Z365559828B0BC01","INVOICE_NO":"X511081485","CARTON_NO":"ZS060125A2651048","PALLET_NO":"MSZW2631800246","MODEL_NO":"G101STN01-4/01","FINAL_GRADE":"Z","PART_NO":"97.10G08.401","STOCK_IN_WEEK":"202544"},{"SHIPPING_TIME":"3/18/2026 3:44:43 PM","SHIPPING_NO":"431S06Z365559828C0BC01","INVOICE_NO":"X511081485","CARTON_NO":"ZS060125A2651065","PALLET_NO":"MSZW2631800246","MODEL_NO":"G101STN01-4/01","FINAL_GRADE":"Z","PART_NO":"97.10G08.401","STOCK_IN_WEEK":"202544"},{"SHIPPING_TIME":"3/18/2026 3:44:43 PM","SHIPPING_NO":"431S06Z365559828M0AB01","INVOICE_NO":"X511081485","CARTON_NO":"ZS060125A2651065","PALLET_NO":"MSZW2631800246","MODEL_NO":"G101STN01-4/01","FINAL_GRADE":"Z","PART_NO":"97.10G08.401","STOCK_IN_WEEK":"202544"},{"SHIPPING_TIME":"3/18/2026 3:44:43 PM","SHIPPING_NO":"431S06Z365559828M0BC01","INVOICE_NO":"X511081485","CARTON_NO":"ZS060125A2651065","PALLET_NO":"MSZW2631800246","MODEL_NO":"G101STN01-4/01","FINAL_GRADE":"Z","PART_NO":"97.10G08.401","STOCK_IN_WEEK":"202544"},{"SHIPPING_TIME":"3/18/2026 3:44:43 PM","SHIPPING_NO":"431S06Z365559828N0AE01","INVOICE_NO":"X511081485","CARTON_NO":"ZS060125A2651065","PALLET_NO":"MSZW2631800246","MODEL_NO":"G101STN01-4/01","FINAL_GRADE":"Z","PART_NO":"97.10G08.401","STOCK_IN_WEEK":"202544"},{"SHIPPING_TIME":"3/18/2026 3:44:43 PM","SHIPPING_NO":"431S06Z365559828N0BA01","INVOICE_NO":"X511081485","CARTON_NO":"ZS060125A2651065","PALLET_NO":"MSZW2631800246","MODEL_NO":"G101STN01-4/01","FINAL_GRADE":"Z","PART_NO":"97.10G08.401","STOCK_IN_WEEK":"202544"},{"SHIPPING_TIME":"3/18/2026 3:44:43 PM","SHIPPING_NO":"431S06Z365559828N0DB01","INVOICE_NO":"X511081485","CARTON_NO":"ZS060125A2651065","PALLET_NO":"MSZW2631800246","MODEL_NO":"G101STN01-4/01","FINAL_GRADE":"Z","PART_NO":"97.10G08.401","STOCK_IN_WEEK":"202544"},{"SHIPPING_TIME":"3/18/2026 3:44:43 PM","SHIPPING_NO":"431S06Z365559828N0EB01","INVOICE_NO":"X511081485","CARTON_NO":"ZS060125A2651048","PALLET_NO":"MSZW2631800246","MODEL_NO":"G101STN01-4/01","FINAL_GRADE":"Z","PART_NO":"97.10G08.401","STOCK_IN_WEEK":"202544"},{"SHIPPING_TIME":"3/18/2026 3:44:43 PM","SHIPPING_NO":"431S06Z365559828N0EH01","INVOICE_NO":"X511081485","CARTON_NO":"ZS060125A2651065","PALLET_NO":"MSZW2631800246","MODEL_NO":"G101STN01-4/01","FINAL_GRADE":"Z","PART_NO":"97.10G08.401","STOCK_IN_WEEK":"202544"},{"SHIPPING_TIME":"3/18/2026 3:44:43 PM","SHIPPING_NO":"431S06Z365559828T0AB01","INVOICE_NO":"X511081485","CARTON_NO":"ZS060125B1051002","PALLET_NO":"MSZW2631800246","MODEL_NO":"G101STN01-4/01","FINAL_GRADE":"Z","PART_NO":"97.10G08.401","STOCK_IN_WEEK":"202544"},{"SHIPPING_TIME":"3/18/2026 3:44:43 PM","SHIPPING_NO":"431S06Z365559828T0BB01","INVOICE_NO":"X511081485","CARTON_NO":"ZS060125A2651048","PALLET_NO":"MSZW2631800246","MODEL_NO":"G101STN01-4/01","FINAL_GRADE":"Z","PART_NO":"97.10G08.401","STOCK_IN_WEEK":"202544"},{"SHIPPING_TIME":"3/18/2026 3:44:43 PM","SHIPPING_NO":"431S06Z365559833M0AD01","INVOICE_NO":"X511081485","CARTON_NO":"ZS060125A2651065","PALLET_NO":"MSZW2631800246","MODEL_NO":"G101STN01-4/01","FINAL_GRADE":"Z","PART_NO":"97.10G08.401","STOCK_IN_WEEK":"202544"},{"SHIPPING_TIME":"3/18/2026 3:44:43 PM","SHIPPING_NO":"431S06Z365559833X0AE01","INVOICE_NO":"X511081485","CARTON_NO":"ZS060125A2651065","PALLET_NO":"MSZW2631800246","MODEL_NO":"G101STN01-4/01","FINAL_GRADE":"Z","PART_NO":"97.10G08.401","STOCK_IN_WEEK":"202544"},{"SHIPPING_TIME":"3/18/2026 3:44:43 PM","SHIPPING_NO":"431S06Z365559833X0BF01","INVOICE_NO":"X511081485","CARTON_NO":"ZS060125A2651048","PALLET_NO":"MSZW2631800246","MODEL_NO":"G101STN01-4/01","FINAL_GRADE":"Z","PART_NO":"97.10G08.401","STOCK_IN_WEEK":"202544"},{"SHIPPING_TIME":"3/18/2026 3:44:43 PM","SHIPPING_NO":"431S06Z365559833X0BG01","INVOICE_NO":"X511081485","CARTON_NO":"ZS060125A2651048","PALLET_NO":"MSZW2631800246","MODEL_NO":"G101STN01-4/01","FINAL_GRADE":"Z","PART_NO":"97.10G08.401","STOCK_IN_WEEK":"202544"},{"SHIPPING_TIME":"3/18/2026 3:44:43 PM","SHIPPING_NO":"431S06Z365559834D0EH01","INVOICE_NO":"X511081485","CARTON_NO":"ZS060125A2651048","PALLET_NO":"MSZW2631800246","MODEL_NO":"G101STN01-4/01","FINAL_GRADE":"Z","PART_NO":"97.10G08.401","STOCK_IN_WEEK":"202544"},{"SHIPPING_TIME":"3/18/2026 3:44:43 PM","SHIPPING_NO":"431S06Z365559834F0AD01","INVOICE_NO":"X511081485","CARTON_NO":"ZS060125A2651048","PALLET_NO":"MSZW2631800246","MODEL_NO":"G101STN01-4/01","FINAL_GRADE":"Z","PART_NO":"97.10G08.401","STOCK_IN_WEEK":"202544"},{"SHIPPING_TIME":"3/18/2026 3:44:43 PM","SHIPPING_NO":"431S06Z365559834F0BE01","INVOICE_NO":"X511081485","CARTON_NO":"ZS060125A2651048","PALLET_NO":"MSZW2631800246","MODEL_NO":"G101STN01-4/01","FINAL_GRADE":"Z","PART_NO":"97.10G08.401","STOCK_IN_WEEK":"202544"},{"SHIPPING_TIME":"3/18/2026 3:44:43 PM","SHIPPING_NO":"431S06Z365559834F0CD01","INVOICE_NO":"X511081485","CARTON_NO":"ZS060125A2651048","PALLET_NO":"MSZW2631800246","MODEL_NO":"G101STN01-4/01","FINAL_GRADE":"Z","PART_NO":"97.10G08.401","STOCK_IN_WEEK":"202544"},{"SHIPPING_TIME":"3/18/2026 3:44:43 PM","SHIPPING_NO":"431S06Z365559834F0DB01","INVOICE_NO":"X511081485","CARTON_NO":"ZS060125A2651065","PALLET_NO":"MSZW2631800246","MODEL_NO":"G101STN01-4/01","FINAL_GRADE":"Z","PART_NO":"97.10G08.401","STOCK_IN_WEEK":"202544"},{"SHIPPING_TIME":"3/18/2026 3:44:43 PM","SHIPPING_NO":"431S06Z365559834F0DH01","INVOICE_NO":"X511081485","CARTON_NO":"ZS060125A2651065","PALLET_NO":"MSZW2631800246","MODEL_NO":"G101STN01-4/01","FINAL_GRADE":"Z","PART_NO":"97.10G08.401","STOCK_IN_WEEK":"202544"},{"SHIPPING_TIME":"3/18/2026 3:44:43 PM","SHIPPING_NO":"431S06Z365559834F0EA01","INVOICE_NO":"X511081485","CARTON_NO":"ZS060125A2651048","PALLET_NO":"MSZW2631800246","MODEL_NO":"G101STN01-4/01","FINAL_GRADE":"Z","PART_NO":"97.10G08.401","STOCK_IN_WEEK":"202544"},{"SHIPPING_TIME":"3/18/2026 3:44:43 PM","SHIPPING_NO":"431S06Z365559834F0EF01","INVOICE_NO":"X511081485","CARTON_NO":"ZS060125A2651048","PALLET_NO":"MSZW2631800246","MODEL_NO":"G101STN01-4/01","FINAL_GRADE":"Z","PART_NO":"97.10G08.401","STOCK_IN_WEEK":"202544"},{"SHIPPING_TIME":"3/18/2026 3:44:43 PM","SHIPPING_NO":"431S06Z365559834H0BA01","INVOICE_NO":"X511081485","CARTON_NO":"ZS060125B1051002","PALLET_NO":"MSZW2631800246","MODEL_NO":"G101STN01-4/01","FINAL_GRADE":"Z","PART_NO":"97.10G08.401","STOCK_IN_WEEK":"202544"},{"SHIPPING_TIME":"3/18/2026 3:44:43 PM","SHIPPING_NO":"431S06Z365559834K0AD01","INVOICE_NO":"X511081485","CARTON_NO":"ZS060125A2651065","PALLET_NO":"MSZW2631800246","MODEL_NO":"G101STN01-4/01","FINAL_GRADE":"Z","PART_NO":"97.10G08.401","STOCK_IN_WEEK":"202544"},{"SHIPPING_TIME":"3/18/2026 3:44:43 PM","SHIPPING_NO":"431S06Z365559834K0AF01","INVOICE_NO":"X511081485","CARTON_NO":"ZS060125A2651048","PALLET_NO":"MSZW2631800246","MODEL_NO":"G101STN01-4/01","FINAL_GRADE":"Z","PART_NO":"97.10G08.401","STOCK_IN_WEEK":"202544"},{"SHIPPING_TIME":"3/18/2026 3:44:43 PM","SHIPPING_NO":"431S06Z365559834K0DB01","INVOICE_NO":"X511081485","CARTON_NO":"ZS060125A2651048","PALLET_NO":"MSZW2631800246","MODEL_NO":"G101STN01-4/01","FINAL_GRADE":"Z","PART_NO":"97.10G08.401","STOCK_IN_WEEK":"202544"},{"SHIPPING_TIME":"3/18/2026 3:44:43 PM","SHIPPING_NO":"431S06Z365559834K0DD01","INVOICE_NO":"X511081485","CARTON_NO":"ZS060125A2651065","PALLET_NO":"MSZW2631800246","MODEL_NO":"G101STN01-4/01","FINAL_GRADE":"Z","PART_NO":"97.10G08.401","STOCK_IN_WEEK":"202544"},{"SHIPPING_TIME":"3/18/2026 3:44:43 PM","SHIPPING_NO":"431S06Z365559834K0EG01","INVOICE_NO":"X511081485","CARTON_NO":"ZS060125A2651065","PALLET_NO":"MSZW2631800246","MODEL_NO":"G101STN01-4/01","FINAL_GRADE":"Z","PART_NO":"97.10G08.401","STOCK_IN_WEEK":"202544"},{"SHIPPING_TIME":"3/18/2026 3:44:43 PM","SHIPPING_NO":"431S06Z365559834M0BE01","INVOICE_NO":"X511081485","CARTON_NO":"ZS060125A2651048","PALLET_NO":"MSZW2631800246","MODEL_NO":"G101STN01-4/01","FINAL_GRADE":"Z","PART_NO":"97.10G08.401","STOCK_IN_WEEK":"202544"},{"SHIPPING_TIME":"3/18/2026 3:44:43 PM","SHIPPING_NO":"431S06Z365559834M0BF01","INVOICE_NO":"X511081485","CARTON_NO":"ZS060125A2651048","PALLET_NO":"MSZW2631800246","MODEL_NO":"G101STN01-4/01","FINAL_GRADE":"Z","PART_NO":"97.10G08.401","STOCK_IN_WEEK":"202544"},{"SHIPPING_TIME":"3/18/2026 3:44:43 PM","SHIPPING_NO":"431S06Z365559834S0DA01","INVOICE_NO":"X511081485","CARTON_NO":"ZS060125A2651065","PALLET_NO":"MSZW2631800246","MODEL_NO":"G101STN01-4/01","FINAL_GRADE":"Z","PART_NO":"97.10G08.401","STOCK_IN_WEEK":"202544"},{"SHIPPING_TIME":"3/18/2026 3:44:43 PM","SHIPPING_NO":"431S06Z3655598Q7S0CB01","INVOICE_NO":"X511081485","CARTON_NO":"ZS060125A2651048","PALLET_NO":"MSZW2631800246","MODEL_NO":"G101STN01-4/01","FINAL_GRADE":"Z","PART_NO":"97.10G08.401","STOCK_IN_WEEK":"202544"},{"SHIPPING_TIME":"3/18/2026 3:44:43 PM","SHIPPING_NO":"431S06Z3655598Q7S0CE01","INVOICE_NO":"X511081485","CARTON_NO":"ZS060125A2651048","PALLET_NO":"MSZW2631800246","MODEL_NO":"G101STN01-4/01","FINAL_GRADE":"Z","PART_NO":"97.10G08.401","STOCK_IN_WEEK":"202544"},{"SHIPPING_TIME":"3/18/2026 3:44:43 PM","SHIPPING_NO":"431S06Z3655598Q7S0DG01","INVOICE_NO":"X511081485","CARTON_NO":"ZS060125A2651048","PALLET_NO":"MSZW2631800246","MODEL_NO":"G101STN01-4/01","FINAL_GRADE":"Z","PART_NO":"97.10G08.401","STOCK_IN_WEEK":"202544"},{"SHIPPING_TIME":"3/18/2026 3:44:43 PM","SHIPPING_NO":"431S06Z3655598Q7S0EC01","INVOICE_NO":"X511081485","CARTON_NO":"ZS060125A2651048","PALLET_NO":"MSZW2631800246","MODEL_NO":"G101STN01-4/01","FINAL_GRADE":"Z","PART_NO":"97.10G08.401","STOCK_IN_WEEK":"202544"},{"SHIPPING_TIME":"3/18/2026 3:44:43 PM","SHIPPING_NO":"431S06Z3655598R0C0EC01","INVOICE_NO":"X511081485","CARTON_NO":"ZS060125A2651065","PALLET_NO":"MSZW2631800246","MODEL_NO":"G101STN01-4/01","FINAL_GRADE":"Z","PART_NO":"97.10G08.401","STOCK_IN_WEEK":"202544"},{"SHIPPING_TIME":"3/18/2026 3:44:43 PM","SHIPPING_NO":"431S06Z3655598R0W0AC01","INVOICE_NO":"X511081485","CARTON_NO":"ZS060125A2651065","PALLET_NO":"MSZW2631800246","MODEL_NO":"G101STN01-4/01","FINAL_GRADE":"Z","PART_NO":"97.10G08.401","STOCK_IN_WEEK":"202544"},{"SHIPPING_TIME":"3/18/2026 3:44:43 PM","SHIPPING_NO":"431S06Z3655598R0W0AG01","INVOICE_NO":"X511081485","CARTON_NO":"ZS060125A2651065","PALLET_NO":"MSZW2631800246","MODEL_NO":"G101STN01-4/01","FINAL_GRADE":"Z","PART_NO":"97.10G08.401","STOCK_IN_WEEK":"202544"},{"SHIPPING_TIME":"3/18/2026 3:44:43 PM","SHIPPING_NO":"431S06Z3655598R0W0CG01","INVOICE_NO":"X511081485","CARTON_NO":"ZS060125A2651048","PALLET_NO":"MSZW2631800246","MODEL_NO":"G101STN01-4/01","FINAL_GRADE":"Z","PART_NO":"97.10G08.401","STOCK_IN_WEEK":"202544"},{"SHIPPING_TIME":"3/18/2026 3:44:43 PM","SHIPPING_NO":"431S06Z3655598R0W0CH01","INVOICE_NO":"X511081485","CARTON_NO":"ZS060125A2651048","PALLET_NO":"MSZW2631800246","MODEL_NO":"G101STN01-4/01","FINAL_GRADE":"Z","PART_NO":"97.10G08.401","STOCK_IN_WEEK":"202544"},{"SHIPPING_TIME":"3/18/2026 3:44:43 PM","SHIPPING_NO":"102S06Z3656598R0X0AG01","INVOICE_NO":"X511081485","CARTON_NO":"ZS06012630551002","PALLET_NO":"MSZW2631800246","MODEL_NO":"G101STN01-4/01","FINAL_GRADE":"Z","PART_NO":"97.10G08.401","STOCK_IN_WEEK":"202610"},{"SHIPPING_TIME":"3/18/2026 3:44:43 PM","SHIPPING_NO":"431S06Z365559980X0AF01","INVOICE_NO":"X511081485","CARTON_NO":"ZS060125A2651065","PALLET_NO":"MSZW2631800246","MODEL_NO":"G101STN01-4/01","FINAL_GRADE":"Z","PART_NO":"97.10G08.401","STOCK_IN_WEEK":"202544"},{"SHIPPING_TIME":"3/18/2026 3:44:43 PM","SHIPPING_NO":"431S06Z365559980X0DA01","INVOICE_NO":"X511081485","CARTON_NO":"ZS060125A2651065","PALLET_NO":"MSZW2631800246","MODEL_NO":"G101STN01-4/01","FINAL_GRADE":"Z","PART_NO":"97.10G08.401","STOCK_IN_WEEK":"202544"},{"SHIPPING_TIME":"3/18/2026 3:44:43 PM","SHIPPING_NO":"431S06Z365559980X0DC01","INVOICE_NO":"X511081485","CARTON_NO":"ZS060125B1051002","PALLET_NO":"MSZW2631800246","MODEL_NO":"G101STN01-4/01","FINAL_GRADE":"Z","PART_NO":"97.10G08.401","STOCK_IN_WEEK":"202544"},{"SHIPPING_TIME":"3/18/2026 3:44:43 PM","SHIPPING_NO":"431S06Z365559980X0DH01","INVOICE_NO":"X511081485","CARTON_NO":"ZS060125A2651065","PALLET_NO":"MSZW2631800246","MODEL_NO":"G101STN01-4/01","FINAL_GRADE":"Z","PART_NO":"97.10G08.401","STOCK_IN_WEEK":"202544"},{"SHIPPING_TIME":"3/18/2026 3:44:43 PM","SHIPPING_NO":"431S06Z365559981B0BF01","INVOICE_NO":"X511081485","CARTON_NO":"ZS060125A2651065","PALLET_NO":"MSZW2631800246","MODEL_NO":"G101STN01-4/01","FINAL_GRADE":"Z","PART_NO":"97.10G08.401","STOCK_IN_WEEK":"202544"},{"SHIPPING_TIME":"3/18/2026 3:44:43 PM","SHIPPING_NO":"431S06Z365559981B0BH01","INVOICE_NO":"X511081485","CARTON_NO":"ZS060125A2651065","PALLET_NO":"MSZW2631800246","MODEL_NO":"G101STN01-4/01","FINAL_GRADE":"Z","PART_NO":"97.10G08.401","STOCK_IN_WEEK":"202544"},{"SHIPPING_TIME":"3/18/2026 3:44:43 PM","SHIPPING_NO":"433S06Z365559981B0DA01","INVOICE_NO":"X511081485","CARTON_NO":"ZS060125A2651065","PALLET_NO":"MSZW2631800246","MODEL_NO":"G101STN01-4/01","FINAL_GRADE":"Z","PART_NO":"97.10G08.401","STOCK_IN_WEEK":"202544"},{"SHIPPING_TIME":"3/18/2026 3:44:43 PM","SHIPPING_NO":"431S06Z365559981D0AA01","INVOICE_NO":"X511081485","CARTON_NO":"ZS060125A2651065","PALLET_NO":"MSZW2631800246","MODEL_NO":"G101STN01-4/01","FINAL_GRADE":"Z","PART_NO":"97.10G08.401","STOCK_IN_WEEK":"202544"},{"SHIPPING_TIME":"3/18/2026 3:44:43 PM","SHIPPING_NO":"431S06Z365559981F0BB01","INVOICE_NO":"X511081485","CARTON_NO":"ZS060125A2651065","PALLET_NO":"MSZW2631800246","MODEL_NO":"G101STN01-4/01","FINAL_GRADE":"Z","PART_NO":"97.10G08.401","STOCK_IN_WEEK":"202544"},{"SHIPPING_TIME":"3/18/2026 3:44:43 PM","SHIPPING_NO":"431S06Z365559981F0BF01","INVOICE_NO":"X511081485","CARTON_NO":"ZS060125A2651065","PALLET_NO":"MSZW2631800246","MODEL_NO":"G101STN01-4/01","FINAL_GRADE":"Z","PART_NO":"97.10G08.401","STOCK_IN_WEEK":"202544"},{"SHIPPING_TIME":"3/18/2026 3:44:43 PM","SHIPPING_NO":"431S06Z365559982A0BE01","INVOICE_NO":"X511081485","CARTON_NO":"ZS060125A2651065","PALLET_NO":"MSZW2631800246","MODEL_NO":"G101STN01-4/01","FINAL_GRADE":"Z","PART_NO":"97.10G08.401","STOCK_IN_WEEK":"202544"},{"SHIPPING_TIME":"3/18/2026 3:44:43 PM","SHIPPING_NO":"431S06Z365559982J0AG01","INVOICE_NO":"X511081485","CARTON_NO":"ZS060125A2651048","PALLET_NO":"MSZW2631800246","MODEL_NO":"G101STN01-4/01","FINAL_GRADE":"Z","PART_NO":"97.10G08.401","STOCK_IN_WEEK":"202544"},{"SHIPPING_TIME":"3/18/2026 3:44:43 PM","SHIPPING_NO":"431S06Z365559982J0BF01","INVOICE_NO":"X511081485","CARTON_NO":"ZS060125A2651065","PALLET_NO":"MSZW2631800246","MODEL_NO":"G101STN01-4/01","FINAL_GRADE":"Z","PART_NO":"97.10G08.401","STOCK_IN_WEEK":"202544"},{"SHIPPING_TIME":"3/18/2026 3:44:43 PM","SHIPPING_NO":"431S06Z365559982J0CB01","INVOICE_NO":"X511081485","CARTON_NO":"ZS060125A2651048","PALLET_NO":"MSZW2631800246","MODEL_NO":"G101STN01-4/01","FINAL_GRADE":"Z","PART_NO":"97.10G08.401","STOCK_IN_WEEK":"202544"},{"SHIPPING_TIME":"3/18/2026 3:44:43 PM","SHIPPING_NO":"431S06Z365559982J0EC01","INVOICE_NO":"X511081485","CARTON_NO":"ZS060125A2651048","PALLET_NO":"MSZW2631800246","MODEL_NO":"G101STN01-4/01","FINAL_GRADE":"Z","PART_NO":"97.10G08.401","STOCK_IN_WEEK":"202544"},{"SHIPPING_TIME":"3/18/2026 3:44:43 PM","SHIPPING_NO":"431S06Z365559982M0AH01","INVOICE_NO":"X511081485","CARTON_NO":"ZS060125A2651048","PALLET_NO":"MSZW2631800246","MODEL_NO":"G101STN01-4/01","FINAL_GRADE":"Z","PART_NO":"97.10G08.401","STOCK_IN_WEEK":"202544"},{"SHIPPING_TIME":"3/18/2026 3:44:43 PM","SHIPPING_NO":"431S06Z365559982N0AC01","INVOICE_NO":"X511081485","CARTON_NO":"ZS060125A2651048","PALLET_NO":"MSZW2631800246","MODEL_NO":"G101STN01-4/01","FINAL_GRADE":"Z","PART_NO":"97.10G08.401","STOCK_IN_WEEK":"202544"},{"SHIPPING_TIME":"3/18/2026 3:44:43 PM","SHIPPING_NO":"431S06Z365559982N0BG01","INVOICE_NO":"X511081485","CARTON_NO":"ZS060125A2651048","PALLET_NO":"MSZW2631800246","MODEL_NO":"G101STN01-4/01","FINAL_GRADE":"Z","PART_NO":"97.10G08.401","STOCK_IN_WEEK":"202544"},{"SHIPPING_TIME":"3/18/2026 3:44:43 PM","SHIPPING_NO":"431S06Z365559982N0DC01","INVOICE_NO":"X511081485","CARTON_NO":"ZS060125A2651048","PALLET_NO":"MSZW2631800246","MODEL_NO":"G101STN01-4/01","FINAL_GRADE":"Z","PART_NO":"97.10G08.401","STOCK_IN_WEEK":"202544"},{"SHIPPING_TIME":"3/18/2026 3:44:43 PM","SHIPPING_NO":"431S06Z365559982N0DF01","INVOICE_NO":"X511081485","CARTON_NO":"ZS060125A2651048","PALLET_NO":"MSZW2631800246","MODEL_NO":"G101STN01-4/01","FINAL_GRADE":"Z","PART_NO":"97.10G08.401","STOCK_IN_WEEK":"202544"},{"SHIPPING_TIME":"3/18/2026 3:44:43 PM","SHIPPING_NO":"431S06Z365559982N0DG01","INVOICE_NO":"X511081485","CARTON_NO":"ZS060125A2651048","PALLET_NO":"MSZW2631800246","MODEL_NO":"G101STN01-4/01","FINAL_GRADE":"Z","PART_NO":"97.10G08.401","STOCK_IN_WEEK":"202544"},{"SHIPPING_TIME":"3/18/2026 3:44:43 PM","SHIPPING_NO":"431S06Z365559982N0DH01","INVOICE_NO":"X511081485","CARTON_NO":"ZS060125A2651048","PALLET_NO":"MSZW2631800246","MODEL_NO":"G101STN01-4/01","FINAL_GRADE":"Z","PART_NO":"97.10G08.401","STOCK_IN_WEEK":"202544"},{"SHIPPING_TIME":"3/18/2026 3:44:43 PM","SHIPPING_NO":"431S06Z365559982U0EH01","INVOICE_NO":"X511081485","CARTON_NO":"ZS060125A2651065","PALLET_NO":"MSZW2631800246","MODEL_NO":"G101STN01-4/01","FINAL_GRADE":"Z","PART_NO":"97.10G08.401","STOCK_IN_WEEK":"202544"},{"SHIPPING_TIME":"3/18/2026 3:44:43 PM","SHIPPING_NO":"431S06Z365559984A0AA01","INVOICE_NO":"X511081485","CARTON_NO":"ZS060125A2651065","PALLET_NO":"MSZW2631800246","MODEL_NO":"G101STN01-4/01","FINAL_GRADE":"Z","PART_NO":"97.10G08.401","STOCK_IN_WEEK":"202544"},{"SHIPPING_TIME":"3/18/2026 3:44:43 PM","SHIPPING_NO":"431S06Z365559984A0AB01","INVOICE_NO":"X511081485","CARTON_NO":"ZS060125A2651048","PALLET_NO":"MSZW2631800246","MODEL_NO":"G101STN01-4/01","FINAL_GRADE":"Z","PART_NO":"97.10G08.401","STOCK_IN_WEEK":"202544"},{"SHIPPING_TIME":"3/18/2026 3:44:43 PM","SHIPPING_NO":"431S06Z365559984A0AC01","INVOICE_NO":"X511081485","CARTON_NO":"ZS060125A2651065","PALLET_NO":"MSZW2631800246","MODEL_NO":"G101STN01-4/01","FINAL_GRADE":"Z","PART_NO":"97.10G08.401","STOCK_IN_WEEK":"202544"},{"SHIPPING_TIME":"3/18/2026 3:44:43 PM","SHIPPING_NO":"431S06Z365559984A0CC01","INVOICE_NO":"X511081485","CARTON_NO":"ZS060125A2651048","PALLET_NO":"MSZW2631800246","MODEL_NO":"G101STN01-4/01","FINAL_GRADE":"Z","PART_NO":"97.10G08.401","STOCK_IN_WEEK":"202544"},{"SHIPPING_TIME":"3/18/2026 3:44:43 PM","SHIPPING_NO":"431S06Z365559984A0DB01","INVOICE_NO":"X511081485","CARTON_NO":"ZS060125A2651065","PALLET_NO":"MSZW2631800246","MODEL_NO":"G101STN01-4/01","FINAL_GRADE":"Z","PART_NO":"97.10G08.401","STOCK_IN_WEEK":"202544"},{"SHIPPING_TIME":"3/18/2026 3:44:43 PM","SHIPPING_NO":"431S06Z365559984A0EE01","INVOICE_NO":"X511081485","CARTON_NO":"ZS060125A2651048","PALLET_NO":"MSZW2631800246","MODEL_NO":"G101STN01-4/01","FINAL_GRADE":"Z","PART_NO":"97.10G08.401","STOCK_IN_WEEK":"202544"}]