[{"SHIPPING_TIME":"3/17/2026 11:33:14 AM","SHIPPING_NO":"WL5K4F25NFZZZS1300","INVOICE_NO":"X511081437","CARTON_NO":"ZS13002581300027","PALLET_NO":"MXMW2631400010","MODEL_NO":"P490QAR01.0","FINAL_GRADE":"Z","PART_NO":"97.49P04.000","STOCK_IN_WEEK":"202533"},{"SHIPPING_TIME":"3/17/2026 11:33:14 AM","SHIPPING_NO":"WL5K4F26YDZZZS1300","INVOICE_NO":"X511081437","CARTON_NO":"ZS13002581300027","PALLET_NO":"MXMW2631400010","MODEL_NO":"P490QAR01.0","FINAL_GRADE":"Z","PART_NO":"97.49P04.000","STOCK_IN_WEEK":"202534"},{"SHIPPING_TIME":"3/17/2026 11:33:14 AM","SHIPPING_NO":"WL5K4F28YFZZZS1300","INVOICE_NO":"X511081437","CARTON_NO":"ZS13002581300027","PALLET_NO":"MXMW2631400010","MODEL_NO":"P490QAR01.0","FINAL_GRADE":"Z","PART_NO":"97.49P04.000","STOCK_IN_WEEK":"202533"},{"SHIPPING_TIME":"3/17/2026 11:33:14 AM","SHIPPING_NO":"WL5K4F28YHZZZS1300","INVOICE_NO":"X511081437","CARTON_NO":"ZS13002581300027","PALLET_NO":"MXMW2631400010","MODEL_NO":"P490QAR01.0","FINAL_GRADE":"Z","PART_NO":"97.49P04.000","STOCK_IN_WEEK":"202533"}]